setup.cfg
setup.py
django_file_keeper.egg-info/PKG-INFO
django_file_keeper.egg-info/SOURCES.txt
django_file_keeper.egg-info/dependency_links.txt
django_file_keeper.egg-info/top_level.txt
keeper/__init__.py
keeper/core.py
keeper/management/__init__.py
keeper/management/commands/__init__.py
keeper/management/commands/upload_data_file.py