Metadata-Version: 1.0
Name: django-file-keeper
Version: 0.0.1
Summary: file storage for management command in django
Home-page: https://github.com/spulec/django-file-keeper
Author: Steve Pulec
Author-email: spulec@gmail
License: UNKNOWN
Platform: UNKNOWN
